pyliebherrhomeapi/__init__.py
pyliebherrhomeapi/client.py
pyliebherrhomeapi/const.py
pyliebherrhomeapi/exceptions.py
pyliebherrhomeapi/models.py
pyliebherrhomeapi/py.typed
pyliebherrhomeapi-0.1.0.dist-info/licenses/LICENSE
pyliebherrhomeapi-0.1.0.dist-info/METADATA
pyliebherrhomeapi-0.1.0.dist-info/WHEEL
pyliebherrhomeapi-0.1.0.dist-info/top_level.txt
pyliebherrhomeapi-0.1.0.dist-info/RECORD
