Metadata-Version: 2.4
Name: pyliebherrhomeapi
Version: 0.1.0
Summary: Python library for Liebherr Home API
Author-email: Mario Mett <mario@mett.ee>
License: MIT
Project-URL: Homepage, https://github.com/mettolen/pyliebherrhomeapi
Project-URL: Repository, https://github.com/mettolen/pyliebherrhomeapi
Project-URL: Issues, https://github.com/mettolen/pyliebherrhomeapi/issues
Keywords: liebherr,home-automation,api
Classifier: Development Status :: 3 - Alpha
Classifier: Intended Audience :: Developers
Classifier: Operating System :: OS Independent
Classifier: Programming Language :: Python :: 3
Classifier: Programming Language :: Python :: 3.11
Classifier: Programming Language :: Python :: 3.12
Classifier: Programming Language :: Python :: 3.13
Classifier: Topic :: Home Automation
Requires-Python: >=3.11
License-File: LICENSE
Requires-Dist: aiohttp>=3.9.0
Provides-Extra: dev
Requires-Dist: pytest>=7.0; extra == "dev"
Requires-Dist: pytest-asyncio>=0.21.0; extra == "dev"
Requires-Dist: pytest-cov>=4.0; extra == "dev"
Requires-Dist: pytest-timeout>=2.1.0; extra == "dev"
Requires-Dist: ruff>=0.1.0; extra == "dev"
Requires-Dist: mypy>=1.0; extra == "dev"
Dynamic: license-file
